skautis/ApplicationManagement.py
skautis/ContentManagement.py
skautis/DocumentStorage.py
skautis/Evaluation.py
skautis/Events.py
skautis/Exports.py
skautis/GoogleApps.py
skautis/Grants.py
skautis/Insurance.py
skautis/Journal.py
skautis/Material.py
skautis/Message.py
skautis/OrganizationUnit.py
skautis/Power.py
skautis/Reports.py
skautis/Summary.py
skautis/TelephonyNetwork.py
skautis/UserManagement.py
skautis/Welcome.py
skautis/__init__.py
skautis_py-1.1.41.dist-info/licenses/LICENSE
skautis_py-1.1.41.dist-info/METADATA
skautis_py-1.1.41.dist-info/WHEEL
skautis_py-1.1.41.dist-info/top_level.txt
skautis_py-1.1.41.dist-info/RECORD
